odoo/addons/l10n_es_irnr/README.rst
odoo/addons/l10n_es_irnr/__init__.py
odoo/addons/l10n_es_irnr/__manifest__.py
odoo/addons/l10n_es_irnr/i18n/ca.po
odoo/addons/l10n_es_irnr/i18n/es.po
odoo/addons/l10n_es_irnr/i18n/l10n_es_irnr.pot
odoo/addons/l10n_es_irnr/migrations/16.0.1.2.1/pre-migration.py
odoo/addons/l10n_es_irnr/readme/CONFIGURE.rst
odoo/addons/l10n_es_irnr/readme/CONTRIBUTORS.rst
odoo/addons/l10n_es_irnr/readme/DESCRIPTION.rst
odoo/addons/l10n_es_irnr/readme/ROADMAP.rst
odoo/addons/l10n_es_irnr/readme/USAGE.rst
odoo/addons/l10n_es_irnr/static/description/icon.png
odoo/addons/l10n_es_irnr/static/description/index.html
odoo_addon_l10n_es_irnr-16.0.1.2.1.2.dist-info/METADATA
odoo_addon_l10n_es_irnr-16.0.1.2.1.2.dist-info/WHEEL
odoo_addon_l10n_es_irnr-16.0.1.2.1.2.dist-info/top_level.txt
odoo_addon_l10n_es_irnr-16.0.1.2.1.2.dist-info/RECORD
